{"code": "003230", "name": "삼양식품(주)", "sector": "10", "last_close": 1145000.0, "model_trained_on": "2026-06-17", "rank": 119, "universe": 227, "percentile": 47.8, "avoid_risk_pct": 52.2, "label": "중립", "event_warning": null, "consensus": {"target": 1865000.0, "opinion": 4.0, "upside_pct": 62.9}, "horizons": {"21": {"label": "단기(1개월)", "direction": "하락", "ret_pct": -0.0, "price": 1144824, "low": 983556, "high": 1332241, "dir_acc": 52.6}, "63": {"label": "중기(3개월)", "direction": "하락", "ret_pct": -3.4, "price": 1105963, "low": 877809, "high": 1514597, "dir_acc": 54.5}, "126": {"label": "장기(6개월)", "direction": "하락", "ret_pct": -4.9, "price": 1089424, "low": 758268, "high": 1699498, "dir_acc": 55.1}}}