{"code": "010120", "name": "엘에스일렉트릭 주식회사", "sector": "28", "last_close": 255000.0, "model_trained_on": "2026-06-17", "rank": 19, "universe": 227, "percentile": 92.0, "avoid_risk_pct": 8.0, "label": "매수 후보", "event_warning": {"category": "treasury_disposal", "label": "자기주식처분", "days_ago": 83, "severe": false, "date": "2026-03-26"}, "consensus": {"target": 260000.0, "opinion": 4.0, "upside_pct": 2.0}, "horizons": {"21": {"label": "단기(1개월)", "direction": "하락", "ret_pct": -3.0, "price": 247341, "low": 201378, "high": 339598, "dir_acc": 52.9}, "63": {"label": "중기(3개월)", "direction": "상승", "ret_pct": 0.9, "price": 257235, "low": 184876, "high": 405874, "dir_acc": 54.3}, "126": {"label": "장기(6개월)", "direction": "하락", "ret_pct": -4.2, "price": 244388, "low": 144796, "high": 424048, "dir_acc": 55.2}}}